MANIFEST.in
README
setup.py
elaphe/__init__.py
elaphe/__version__.py
elaphe/auspost.py
elaphe/azteccode.py
elaphe/base.py
elaphe/codabar.py
elaphe/code11.py
elaphe/code128.py
elaphe/code25.py
elaphe/code39.py
elaphe/code93.py
elaphe/datamatrix.py
elaphe/ean.py
elaphe/i2of5.py
elaphe/japanpost.py
elaphe/kix.py
elaphe/maxicode.py
elaphe/msi.py
elaphe/onecode.py
elaphe/pdf417.py
elaphe/pharmacode.py
elaphe/plessey.py
elaphe/postnet.py
elaphe/qrcode.py
elaphe/raw.py
elaphe/royalmail.py
elaphe/rss.py
elaphe/symbol.py
elaphe/upc.py
elaphe/util.py
elaphe.egg-info/PKG-INFO
elaphe.egg-info/SOURCES.txt
elaphe.egg-info/dependency_links.txt
elaphe.egg-info/not-zip-safe
elaphe.egg-info/requires.txt
elaphe.egg-info/top_level.txt
elaphe/postscriptbarcode/LICENSE
elaphe/postscriptbarcode/barcode.ps