Metadata-Version: 1.0
Name: elaphe
Version: 0.6.0
Summary: Generates various barcodes using barcode.ps and PIL.
Home-page: http://bitbucket.org/whosaysni/elaphe/
Author: Yasushi Masuda
Author-email: whosaysni at gmail dot com
License: New BSD
Keywords: barcode convert postscript image graphics
Platform: UNKNOWN
Classifier: Development Status :: 4 - Beta
Classifier: Environment :: Console
Classifier: Intended Audience :: Developers
Classifier: License :: OSI Approved :: BSD License
Classifier: Operating System :: OS Independent
Classifier: Programming Language :: Python
Classifier: Topic :: Software Development :: Libraries :: Python Modules
